rrlpy-0.1.4.dist-info/METADATA
rrlpy-0.1.4.dist-info/WHEEL
rrlpy-0.1.4.dist-info/entry_points.txt
rrlpy-0.1.4.dist-info/licenses/LICENSE
rrlpy/__init__.py
rrlpy/cli.py
rrlpy/continuum/__init__.py
rrlpy/continuum/continuum.py
rrlpy/continuum/core.py
rrlpy/departure/__init__.py
rrlpy/departure/bnbeta.py
rrlpy/departure/tests/test_bnbeta.py
rrlpy/freq/__init__.py
rrlpy/freq/core.py
rrlpy/freq/data/CH.txt
rrlpy/freq/data/OH.txt
rrlpy/freq/data/RRL_3HeIalpha.txt
rrlpy/freq/data/RRL_CIalpha.txt
rrlpy/freq/data/RRL_CIbeta.txt
rrlpy/freq/data/RRL_CIdelta.txt
rrlpy/freq/data/RRL_CIepsilon.txt
rrlpy/freq/data/RRL_CIgamma.txt
rrlpy/freq/data/RRL_CIzeta.txt
rrlpy/freq/data/RRL_HIalpha.txt
rrlpy/freq/data/RRL_HIbeta.txt
rrlpy/freq/data/RRL_HIdelta.txt
rrlpy/freq/data/RRL_HIepsilon.txt
rrlpy/freq/data/RRL_HIgamma.txt
rrlpy/freq/data/RRL_HeIalpha.txt
rrlpy/freq/data/RRL_HeIbeta.txt
rrlpy/freq/data/RRL_HeIgamma.txt
rrlpy/freq/data/RRL_NIalpha.txt
rrlpy/freq/data/RRL_NIbeta.txt
rrlpy/hrrl/__init__.py
rrlpy/hrrl/core.py
rrlpy/linewidth/__init__.py
rrlpy/linewidth/core.py
rrlpy/rrl/__init__.py
rrlpy/rrl/constants.py
rrlpy/rrl/core.py
rrlpy/rrl/rrl.py
rrlpy/rrl/tests/test_core.py
rrlpy/rrl/tests/test_rrl.py
rrlpy/rrlpy.py
rrlpy/synth/__init__.py
rrlpy/synth/layers.py
rrlpy/synth/tests/test_layers.py
rrlpy/utils/__init__.py
rrlpy/utils/core.py
rrlpy-0.1.4.dist-info/RECORD
