Metadata-Version: 2.1
Name: rrlpy
Version: 0.1.4
Summary: Radio Recombination Lines in Python
Home-page: https://github.com/astrofle/RRLpy
Author-Email: Pedro Salas <psalas@nrao.edu>, astrofle <psalas@nrao.edu>
License: GNU GENERAL PUBLIC LICENSE
Classifier: License :: OSI Approved :: GNU General Public License v3 (GPLv3)
Project-URL: Homepage, https://github.com/astrofle/RRLpy
Project-URL: Repository, https://github.com/astrofle/RRLpy
Requires-Python: >=3.5
Requires-Dist: astropy
Requires-Dist: scipy
Requires-Dist: numpy
